{"key":"idp/adapter/RefreshToken/hVvnOhx5HBm6oKPhf9lxYeWgfnrzH8TbbLm9K2sMDV2","payload":{"expires":"2026-01-08T20:20:37.207Z","payload":{"iat":1767817237,"exp":1767903637,"accountId":"http://localhost:3000/doctor/profile/card#me","authTime":1767817236,"grantId":"CNPswjfAzWpD2Zc0F4x1BnWPqg5dzIerD-jYwihUb2s","gty":"authorization_code","resource":"http://example.com/","rotations":0,"scope":"openid offline_access webid ","sessionUid":"4LPXUy4tlO3lDPtctVd5O","kind":"RefreshToken","jti":"hVvnOhx5HBm6oKPhf9lxYeWgfnrzH8TbbLm9K2sMDV2","clientId":"TZ4LdobY9JwNte1HutUBQ","iiat":1767817237}}}